<?xml version="1.0" encoding="utf-8"?>
<akn:akomaNtoso xmlns:akn="http://docs.oasis-open.org/legaldocml/ns/akn/3.0"
                xmlns:ris="http://example.com/0.1/"
                xmlns:xsi="http://www.w3.org/2001/XMLSchema-instance"
                xsi:schemaLocation="http://docs.oasis-open.org/legaldocml/ns/akn/3.0 https://docs.oasis-open.org/legaldocml/akn-core/v1.0/os/part2-specs/schemas/akomantoso30.xsd">

    <akn:judgment name="Beschluss">
        <akn:meta>
            <akn:identification source="#ris">
                <akn:FRBRWork>
                    <akn:FRBRthis value="MPRE088000100"/>
                    <akn:FRBRuri value="MPRE088000100"/>
                    <akn:FRBRalias name="Übergreifende ID" value="fake-uuid-0003"/>
                    <akn:FRBRalias name="Dokumentnummer" value="MPRE088000100" />
                    <akn:FRBRdate eId="Entscheidungsdatum" date="2025-04-09" name="Entscheidungsdatum"/>
                    <akn:FRBRauthor href="#gericht"/>
                    <akn:FRBRcountry value="de"/>
                </akn:FRBRWork>
                <akn:FRBRExpression>
                    <akn:FRBRthis value="MPRE088000100/dokument"/>
                    <akn:FRBRuri value="MPRE088000100/dokument"/>
                    <akn:FRBRdate date="2025-04-09" name="Entscheidungsdatum"/>
                    <akn:FRBRauthor href="#gericht"/>
                    <akn:FRBRlanguage language="deu"/>
                </akn:FRBRExpression>
                <akn:FRBRManifestation>
                    <akn:FRBRthis value="MPRE088000100/dokument.xml"/>
                    <akn:FRBRuri value="MPRE088000100/dokument.xml"/>
                    <akn:FRBRdate date="2025-04-09" name="XML Transformation"/>
                    <akn:FRBRauthor href="#bpatg-dokumentationsstelle"/>
                </akn:FRBRManifestation>
            </akn:identification>
            <akn:classification source="#ris">
                <akn:keyword ris:domainTerm="Schlagwort" dictionary="" showAs="WerbungNeu" value="WerbungNeu"/>
                <akn:keyword ris:domainTerm="Schlagwort" dictionary="" showAs="MarkenName" value="MarkenName"/>
                <akn:keyword ris:domainTerm="Schlagwort" dictionary="" showAs="ReinigungsWert" value="ReinigungsWert"/>
                <akn:keyword ris:domainTerm="Schlagwort" dictionary="" showAs="Testmarkenrecht!!" value="Testmarkenrecht!!"/>
            </akn:classification>
            <akn:analysis source="#ris">
                <akn:otherAnalysis source="#ris">
                    <ris:dokumentarischeKurztexte domainTerm="Dokumentarische Kurztexte">
                        <ris:titelzeile akn:eId="titelzeile" ris:domainTerm="Titelzeile">
                            <akn:p>Beschluss 2.</akn:p>
                        </ris:titelzeile>
                        <ris:orientierungssatz ris:domainTerm="Orientierungssatz">
                            <akn:p>1. Fiktiver Satz zur Beschreibung des Sachverhalts in diesem Fall.</akn:p>
                            <akn:p>2. Testinformationen werden hier exemplarisch dargestellt.</akn:p>
                        </ris:orientierungssatz>
                    </ris:dokumentarischeKurztexte>
                </akn:otherAnalysis>
            </akn:analysis>
            <akn:references source="#ris">
                <akn:TLCOrganization eId="ris" href="" showAs="Rechtsinformationssystem des Bundes"/>
                <akn:TLCOrganization eId="bpatg-dokumentationsstelle" href="" showAs="BPatG"/>
                <akn:TLCOrganization eId="gericht" href="" showAs="BPatG"/>
                <akn:TLCOrganization eId="spruchkoerper" href="" showAs="15. Senat"/>
            </akn:references>
            <akn:proprietary source="ris">
                <ris:meta>
                    <ris:entscheidungstextListe domainTerm="Liste der Entscheidungstexte">
                        <ris:entscheidungstext domainTerm="Entscheidungstext">FiktiverEntscheid2</ris:entscheidungstext>
                    </ris:entscheidungstextListe>
                    <ris:aktenzeichenListe domainTerm="Liste der Aktenzeichen">
                        <ris:aktenzeichen domainTerm="Aktenzeichen" akn:refersTo="#aktenzeichen">AB C 78/90</ris:aktenzeichen>
                    </ris:aktenzeichenListe>
                    <ris:dokumenttyp akn:eId="dokumenttyp" domainTerm="Dokumenttyp">Beschluss</ris:dokumenttyp>
                    <ris:gericht domainTerm="Gericht" akn:refersTo="#gericht">
                        <ris:gerichtstyp domainTerm="Gerichtstyp">BPatG</ris:gerichtstyp>
                        <ris:gerichtsort domainTerm="Gerichtsort">Beispielstadt</ris:gerichtsort>
                        <ris:spruchkoerper domainTerm="Spruchkörper" akn:refersTo="#spruchkoerper">15. Senat</ris:spruchkoerper>
                    </ris:gericht>
                    <ris:rechtskraft domainTerm="Rechtskraft">Keine Angabe</ris:rechtskraft>
                    <ris:sachgebiete domainTerm="Sachgebiete">
                        <ris:sachgebiet domainTerm="Sachgebiet" notation="neu">Testmarkenrecht!!</ris:sachgebiet>
                        <ris:sachgebiet domainTerm="Sachgebiet" notation="neu">Testregulierungsrecht</ris:sachgebiet>
                        <ris:sachgebiet domainTerm="Sachgebiet" notation="neu">Musterrecht (inkl. Beispieldaten)</ris:sachgebiet>
                        <ris:sachgebiet domainTerm="Sachgebiet" notation="neu">Beiswertung2</ris:sachgebiet>
                    </ris:sachgebiete>
                    <ris:dokumentationsstelle domainTerm="Dokumentationsstelle" akn:refersTo="#bpatg-dokumentationsstelle">BPatG</ris:dokumentationsstelle>
                </ris:meta>
            </akn:proprietary>
        </akn:meta>
        <akn:header>
            <akn:p>Beispielheader für den Beschluss 2.</akn:p>
            <akn:p>Aktenzeichen: <akn:docNumber refersTo="#aktenzeichen">AB C 78/90</akn:docNumber></akn:p>
            <akn:p>Entscheidungsdatum: <akn:docDate date="2025-04-09" refersTo="#entscheidungsdatum">09.04.2025</akn:docDate></akn:p>
            <akn:p>Gericht: <akn:courtType refersTo="#gericht">BPatG</akn:courtType></akn:p>
            <akn:p>Dokumenttyp: <akn:docType refersTo="#dokumenttyp">Beschluss</akn:docType></akn:p>
            <akn:p>Kurztitel: <akn:shortTitle>
                <akn:embeddedStructure>
                    <akn:p>Beispielheader für den Beschluss 2.</akn:p>
                </akn:embeddedStructure>
            </akn:shortTitle>
            </akn:p>
        </akn:header>
        <akn:judgmentBody>
            <akn:decision ris:domainTerm="Tenor">
                <akn:p>Der Beschluss enthält fiktive testwerte und Bedingungen.</akn:p>
                <akn:p>Die Verfahrenskosten werden vollständig übernommen.</akn:p>
            </akn:decision>
            <akn:background ris:domainTerm="Tatbestand">
                <akn:hcontainer name="randnummer">
                    <akn:num>1</akn:num>
                    <akn:content>
                        <akn:p>Eine fiktive Schilderung der Sachlage dient hier als Testbeispiel.</akn:p>
                    </akn:content>
                </akn:hcontainer>
            </akn:background>
        </akn:judgmentBody>
    </akn:judgment>
</akn:akomaNtoso>
